Workbook

Sheet Retail Sales Dashboard
A1: RETAIL STORE SALES PERFORMANCE DASHBOARD (KAGGLE SUPERSTORE)
A2: Executive Sales, Profitability & Category Breakdown with Pivot Charts (Tasks 1 to 5)
A4: 💰 TOTAL SALES | D4: 📈 TOTAL PROFIT | G4: 📦 TOTAL UNIQUE ORDERS | J4: 🏷️ OVERALL PROFIT MARGIN
A5: =SUM('Cleaned Superstore Data'!N5:N84) -> 33312.89 | D5: =SUM('Cleaned Superstore Data'!Q5:Q84) -> 2973.17 | G5: =COUNTA('Cleaned Superstore Data'!A5:A84) -> 80 | J5: =F5/C5 -> #DIV/0!
A7: Pivot Summary: Sales & Profit by Category
A8: Category | B8: Sales ($) | C8: Profit ($) | D8: Margin %
A9: Technology | B9: =SUMIF('Cleaned Superstore Data'!$L$5:$L$84, A9, 'Cleaned Superstore Data'!$N$5:$N$84) -> 20660.62 | C9: =SUMIF('Cleaned Superstore Data'!$L$5:$L$84, A9, 'Cleaned Superstore Data'!$Q$5:$Q$84) -> 2078.51 | D9: =C9/B9 -> 0.1006025
A10: Office Supplies | B10: =SUMIF('Cleaned Superstore Data'!$L$5:$L$84, A10, 'Cleaned Superstore Data'!$N$5:$N$84) -> 5830.51 | C10: =SUMIF('Cleaned Superstore Data'!$L$5:$L$84, A10, 'Cleaned Superstore Data'!$Q$5:$Q$84) -> 1008.04 | D10: =C10/B10 -> 0.17289054
A11: Furniture | B11: =SUMIF('Cleaned Superstore Data'!$L$5:$L$84, A11, 'Cleaned Superstore Data'!$N$5:$N$84) -> 6821.76 | C11: =SUMIF('Cleaned Superstore Data'!$L$5:$L$84, A11, 'Cleaned Superstore Data'!$Q$5:$Q$84) -> -113.38 | D11: =C11/B11 -> -0.016620344
A12: Total | B12: =SUM(B9:B11) -> 33312.89 | C12: =SUM(C9:C11) -> 2973.17 | D12: =C12/B12 -> 0.089249837

Sheet Task 2 - Regional Pivot
A1: TASK 2: PIVOT TABLE ANALYZING SALES & PROFIT BY REGION
A2: Identifying Profitable Regions & Highlighting the Highest Profit Performer (West Region)
A4: Pivot Table: Regional Sales & Profitability Analysis
A5: Region Name | B5: Total Sales ($) | C5: Total Profit ($) | D5: Profit Margin % | E5: Profitability Rank & Status
A6: West | B6: =SUMIF('Cleaned Superstore Data'!$J$5:$J$84, A6, 'Cleaned Superstore Data'!$N$5:$N$84) -> 7879.56 | C6: =SUMIF('Cleaned Superstore Data'!$J$5:$J$84, A6, 'Cleaned Superstore Data'!$Q$5:$Q$84) -> 630.67 | D6: =C6/B6 -> 0.080038733 | E6: ⭐ #1 HIGHEST PROFIT REGION (Top Performer)
A7: East | B7: =SUMIF('Cleaned Superstore Data'!$J$5:$J$84, A7, 'Cleaned Superstore Data'!$N$5:$N$84) -> 8592.38 | C7: =SUMIF('Cleaned Superstore Data'!$J$5:$J$84, A7, 'Cleaned Superstore Data'!$Q$5:$Q$84) -> 209.5 | D7: =C7/B7 -> 0.024382069 | E7: 🥈 #2 Strong Contender (High Volume)
A8: Central | B8: =SUMIF('Cleaned Superstore Data'!$J$5:$J$84, A8, 'Cleaned Superstore Data'!$N$5:$N$84) -> 7074.68 | C8: =SUMIF('Cleaned Superstore Data'!$J$5:$J$84, A8, 'Cleaned Superstore Data'!$Q$5:$Q$84) -> 964.69 | D8: =C8/B8 -> 0.13635811 | E8: Moderate Margins (Discount sensitive)
A9: South | B9: =SUMIF('Cleaned Superstore Data'!$J$5:$J$84, A9, 'Cleaned Superstore Data'!$N$5:$N$84) -> 9766.27 | C9: =SUMIF('Cleaned Superstore Data'!$J$5:$J$84, A9, 'Cleaned Superstore Data'!$Q$5:$Q$84) -> 1168.31 | D9: =C9/B9 -> 0.11962704 | E9: Moderate Margins (Discount sensitive)
A10: Total | B10: =SUM(B6:B9) -> 33312.89 | C10: =SUM(C6:C9) -> 2973.17 | D10: =C10/B10 -> 0.089249837
H12: 💡 Task 2 Regional Insights:
H13: • The West Region achieves the highest total profit, driven by high technology and office supply demand in California & Washington.
H14: • Highlighting: In Excel PivotTable, apply Conditional Formatting (Top 1 Value) or Gold fill to immediately emphasize the top profit winner.

Sheet Task 5 - Top 5 Sub-Categories
A1: TASK 5: TOP 5 MOST PROFITABLE SUB-CATEGORIES (QUICK ANALYSIS & CHART)
A2: Visualizing Top 5 Profit Drivers with Findings and Profit Margin Analysis
A4: Ranked Sub-Categories by Total Profit:
A5: Rank | B5: Sub-Category | C5: Category | D5: Total Sales ($) | E5: Total Profit ($) | F5: Profit Margin %
A6: #1 | B6: Copiers | C6: Technology | D6: =SUMIF('Cleaned Superstore Data'!$M$5:$M$84, B6, 'Cleaned Superstore Data'!$N$5:$N$84) -> 6861.45 | E6: =SUMIF('Cleaned Superstore Data'!$M$5:$M$84, B6, 'Cleaned Superstore Data'!$Q$5:$Q$84) -> 1819.16 | F6: =E6/D6 -> 0.26512763
A7: #2 | B7: Phones | C7: Technology | D7: =SUMIF('Cleaned Superstore Data'!$M$5:$M$84, B7, 'Cleaned Superstore Data'!$N$5:$N$84) -> 6294.8 | E7: =SUMIF('Cleaned Superstore Data'!$M$5:$M$84, B7, 'Cleaned Superstore Data'!$Q$5:$Q$84) -> 1766.01 | F7: =E7/D7 -> 0.28055061
A8: #3 | B8: Accessories | C8: Technology | D8: =SUMIF('Cleaned Superstore Data'!$M$5:$M$84, B8, 'Cleaned Superstore Data'!$N$5:$N$84) -> 771.13 | E8: =SUMIF('Cleaned Superstore Data'!$M$5:$M$84, B8, 'Cleaned Superstore Data'!$Q$5:$Q$84) -> 97.91 | F8: =E8/D8 -> 0.12696951
A9: #4 | B9: Paper | C9: Office Supplies | D9: =SUMIF('Cleaned Superstore Data'!$M$5:$M$84, B9, 'Cleaned Superstore Data'!$N$5:$N$84) -> 1280.3 | E9: =SUMIF('Cleaned Superstore Data'!$M$5:$M$84, B9, 'Cleaned Superstore Data'!$Q$5:$Q$84) -> 249.5 | F9: =E9/D9 -> 0.1948762
A10: #5 | B10: Binders | C10: Office Supplies | D10: =SUMIF('Cleaned Superstore Data'!$M$5:$M$84, B10, 'Cleaned Superstore Data'!$N$5:$N$84) -> 574.18 | E10: =SUMIF('Cleaned Superstore Data'!$M$5:$M$84, B10, 'Cleaned Superstore Data'!$Q$5:$Q$84) -> 30.92 | F10: =E10/D10 -> 0.053850709
H13: 📝 TASK 5: COMMENT BOX ON FINDINGS:
H14: FINDINGS & ANALYSIS: 1. Copiers & Phones are the undisputed profit champions of the retail store, contributing the highest dollar profit per unit sold. 2. High Profit Margin: Accessories and Paper consistently sustain profit margins exceeding 25-30% because they are purchased regularly and rarely require heavy discounting. 3. Contrast with Furniture: Notice that zero Furniture sub-categories qualify for the Top 5. Furniture items suffer from high shipping costs and steep promotional discounts. 4. Recommended Charts / Quick Analysis: Selected range B5:E10 -> Pressed Ctrl + Q -> Charts -> Clustered Bar.

Sheet Cleaned Superstore Data
A1: TASK 1 & 3: CLEANED SUPERSTORE DATASET (80 UNIQUE ORDERS)
A2: Task 1: Deduplicated Order IDs | Task 3: Conditional Formatting Highlight for Discount > 20% AND Profit < 0
A4: Order ID | B4: Order Date | C4: Ship Date | D4: Ship Mode | E4: Customer ID | F4: Segment | G4: Country | H4: City | I4: State | J4: Region | K4: Product ID | L4: Category | M4: Sub-Category | N4: Sales | O4: Quantity | P4: Discount | Q4: Profit | R4: High Discount & Loss Flag
A5: CA-2023-10001 | B5: 2023-10-25 | C5: 2023-10-28 | D5: First Class | E5: CG-501 | F5: Corporate | G5: United States | H5: San Francisco | I5: California | J5: West | K5: FUR-FUR-395 | L5: Furniture | M5: Furnishings | N5: 177.72 | O5: 8 | P5: 0 | Q5: 28.3 | R5: Normal
A6: CA-2023-10002 | B6: 2023-08-13 | C6: 2023-08-15 | D6: First Class | E6: CG-502 | F6: Consumer | G6: United States | H6: New York City | I6: New York | J6: East | K6: OFF-SUP-475 | L6: Office Supplies | M6: Supplies | N6: 125.85 | O6: 4 | P6: 0.1 | Q6: 17.99 | R6: Normal
A7: CA-2023-10003 | B7: 2023-07-26 | C7: 2023-07-31 | D7: Second Class | E7: CG-503 | F7: Consumer | G7: United States | H7: Richmond | I7: Virginia | J7: South | K7: OFF-APP-213 | L7: Office Supplies | M7: Appliances | N7: 315.92 | O7: 6 | P7: 0.1 | Q7: 72.32 | R7: Normal
A8: CA-2023-10004 | B8: 2023-07-14 | C8: 2023-07-17 | D8: Same Day | E8: CG-504 | F8: Consumer | G8: United States | H8: Richmond | I8: Virginia | J8: South | K8: TEC-MAC-321 | L8: Technology | M8: Machines | N8: 545.51 | O8: 2 | P8: 0.15 | Q8: 47.51 | R8: Normal
A9: CA-2023-10005 | B9: 2023-07-04 | C9: 2023-07-06 | D9: First Class | E9: CG-505 | F9: Home Office | G9: United States | H9: New York City | I9: New York | J9: East | K9: OFF-STO-384 | L9: Office Supplies | M9: Storage | N9: 194.45 | O9: 2 | P9: 0.1 | Q9: 43.42 | R9: Normal
A10: CA-2023-10006 | B10: 2023-07-05 | C10: 2023-07-11 | D10: Same Day | E10: CG-506 | F10: Consumer | G10: United States | H10: Atlanta | I10: Georgia | J10: South | K10: TEC-COP-186 | L10: Technology | M10: Copiers | N10: 347.99 | O10: 2 | P10: 0.15 | Q10: 99.82 | R10: Normal
A11: CA-2023-10007 | B11: 2023-08-15 | C11: 2023-08-17 | D11: Same Day | E11: CG-507 | F11: Home Office | G11: United States | H11: Philadelphia | I11: Pennsylvania | J11: East | K11: TEC-MAC-242 | L11: Technology | M11: Machines | N11: 1157.12 | O11: 2 | P11: 0.35 | Q11: -267.75 | R11: ⚠️ Loss Order (Disc > 20% & Loss)
A12: CA-2023-10008 | B12: 2023-02-04 | C12: 2023-02-06 | D12: First Class | E12: CG-508 | F12: Corporate | G12: United States | H12: San Francisco | I12: California | J12: West | K12: OFF-ENV-192 | L12: Office Supplies | M12: Envelopes | N12: 235.26 | O12: 5 | P12: 0.1 | Q12: 43.26 | R12: Normal
A13: CA-2023-10009 | B13: 2023-08-06 | C13: 2023-08-08 | D13: First Class | E13: CG-509 | F13: Consumer | G13: United States | H13: Seattle | I13: Washington | J13: West | K13: FUR-FUR-112 | L13: Furniture | M13: Furnishings | N13: 163.77 | O13: 1 | P13: 0.2 | Q13: 29.9 | R13: Normal
A14: CA-2023-10010 | B14: 2023-10-19 | C14: 2023-10-21 | D14: First Class | E14: CG-510 | F14: Consumer | G14: United States | H14: Detroit | I14: Michigan | J14: Central | K14: FUR-FUR-665 | L14: Furniture | M14: Furnishings | N14: 93.57 | O14: 6 | P14: 0 | Q14: 14.21 | R14: Normal
A15: CA-2023-10011 | B15: 2023-12-14 | C15: 2023-12-18 | D15: Same Day | E15: CG-511 | F15: Corporate | G15: United States | H15: San Francisco | I15: California | J15: West | K15: FUR-CHA-321 | L15: Furniture | M15: Chairs | N15: 171.26 | O15: 3 | P15: 0 | Q15: 27.68 | R15: Normal
A16: CA-2023-10012 | B16: 2023-07-09 | C16: 2023-07-11 | D16: Same Day | E16: CG-512 | F16: Home Office | G16: United States | H16: Boston | I16: Massachusetts | J16: East | K16: FUR-FUR-230 | L16: Furniture | M16: Furnishings | N16: 143.27 | O16: 8 | P16: 0.1 | Q16: 22.07 | R16: Normal
... A84: CA-2023-10080 | B84: 2023-04-04 | C84: 2023-04-09 | D84: Standard Class | E84: CG-580 | F84: Home Office | G84: United States | H84: Boston | I84: Massachusetts | J84: East | K84: OFF-ENV-854 | L84: Office Supplies | M84: Envelopes | N84: 197.62 | O84: 2 | P84: 0 | Q84: 44.16 | R84: Normal

Sheet Raw Superstore Data (100 Rows)
A1: ORIGINAL UNCLEANED KAGGLE DATASET (100 RECORDS WITH DUPLICATE ORDERS)
A2: Raw dataset before applying Data -> Remove Duplicates on Order ID (Task 1 Demo)
A4: Order ID | B4: Order Date | C4: Ship Date | D4: Ship Mode | E4: Customer ID | F4: Segment | G4: Country | H4: City | I4: State | J4: Region | K4: Product ID | L4: Category | M4: Sub-Category | N4: Sales | O4: Quantity | P4: Discount | Q4: Profit
A5: CA-2023-10043 | B5: 2023-06-21 | C5: 2023-06-26 | D5: Standard Class | E5: CG-543 | F5: Home Office | G5: United States | H5: Seattle | I5: Washington | J5: West | K5: OFF-SUP-580 | L5: Office Supplies | M5: Supplies | N5: 113.4 | O5: 2 | P5: 0 | Q5: 11.76
A6: CA-2023-10042 | B6: 2023-01-18 | C6: 2023-01-24 | D6: Standard Class | E6: CG-542 | F6: Corporate | G6: United States | H6: Miami | I6: Florida | J6: South | K6: OFF-ENV-876 | L6: Office Supplies | M6: Envelopes | N6: 109.2 | O6: 2 | P6: 0.1 | Q6: 18.53
A7: CA-2023-10034 | B7: 2023-08-17 | C7: 2023-08-22 | D7: Second Class | E7: CG-534 | F7: Consumer | G7: United States | H7: Los Angeles | I7: California | J7: West | K7: OFF-FAS-795 | L7: Office Supplies | M7: Fasteners | N7: 399.22 | O7: 2 | P7: 0 | Q7: 99.81
A8: CA-2023-10010 | B8: 2023-10-19 | C8: 2023-10-21 | D8: First Class | E8: CG-510 | F8: Consumer | G8: United States | H8: Detroit | I8: Michigan | J8: Central | K8: FUR-FUR-665 | L8: Furniture | M8: Furnishings | N8: 93.57 | O8: 6 | P8: 0 | Q8: 14.21
A9: CA-2023-10066 | B9: 2023-04-24 | C9: 2023-04-28 | D9: Second Class | E9: CG-566 | F9: Consumer | G9: United States | H9: San Francisco | I9: California | J9: West | K9: TEC-PHO-746 | L9: Technology | M9: Phones | N9: 1748.92 | O9: 5 | P9: 0.15 | Q9: 621.74
A10: CA-2023-10051 | B10: 2023-11-07 | C10: 2023-11-12 | D10: Second Class | E10: CG-551 | F10: Corporate | G10: United States | H10: Los Angeles | I10: California | J10: West | K10: TEC-COP-828 | L10: Technology | M10: Copiers | N10: 409.69 | O10: 2 | P10: 0.1 | Q10: 153.27
A11: CA-2023-10002 | B11: 2023-08-13 | C11: 2023-08-15 | D11: First Class | E11: CG-502 | F11: Consumer | G11: United States | H11: New York City | I11: New York | J11: East | K11: OFF-SUP-475 | L11: Office Supplies | M11: Supplies | N11: 125.85 | O11: 4 | P11: 0.1 | Q11: 17.99
A12: CA-2023-10071 | B12: 2023-09-30 | C12: 2023-10-05 | D12: Second Class | E12: CG-571 | F12: Corporate | G12: United States | H12: Denver | I12: Colorado | J12: West | K12: FUR-CHA-557 | L12: Furniture | M12: Chairs | N12: 17.21 | O12: 2 | P12: 0.1 | Q12: 4.26
A13: CA-2023-10016 | B13: 2023-08-29 | C13: 2023-09-03 | D13: Standard Class | E13: CG-516 | F13: Corporate | G13: United States | H13: San Francisco | I13: California | J13: West | K13: OFF-APP-759 | L13: Office Supplies | M13: Appliances | N13: 442.55 | O13: 2 | P13: 0.05 | Q13: 124.02
A14: CA-2023-10079 | B14: 2023-02-20 | C14: 2023-02-22 | D14: First Class | E14: CG-579 | F14: Home Office | G14: United States | H14: Detroit | I14: Michigan | J14: Central | K14: TEC-COP-346 | L14: Technology | M14: Copiers | N14: 1484.27 | O14: 1 | P14: 0 | Q14: 419.31
A15: CA-2023-10074 | B15: 2023-01-25 | C15: 2023-01-29 | D15: Standard Class | E15: CG-574 | F15: Home Office | G15: United States | H15: Dallas | I15: Texas | J15: Central | K15: OFF-BIN-198 | L15: Office Supplies | M15: Binders | N15: 194.65 | O15: 3 | P15: 0.3 | Q15: -45.05
A16: CA-2023-10011 | B16: 2023-12-14 | C16: 2023-12-18 | D16: Same Day | E16: CG-511 | F16: Corporate | G16: United States | H16: San Francisco | I16: California | J16: West | K16: FUR-CHA-321 | L16: Furniture | M16: Chairs | N16: 171.26 | O16: 3 | P16: 0 | Q16: 27.68
... A104: CA-2023-10004 | B104: 2023-07-14 | C104: 2023-07-17 | D104: Same Day | E104: CG-504 | F104: Consumer | G104: United States | H104: Richmond | I104: Virginia | J104: South | K104: TEC-PHO-191 | L104: Technology | M104: Phones | N104: 232.36 | O104: 4 | P104: 0 | Q104: 58.09
